<?xml version="1.0" encoding="UTF-8" ?>
<!--
theme name:		GPIBoy
author:			Juliano Dorigão
-->

<theme>
    <formatVersion>7</formatVersion>
        <variables>
            <colorBase>577629</colorBase>
            <colorTextBase>000000</colorTextBase>
            <colorBackground>557c37</colorBackground>

            <!-- Menu -->
            <separatorColorBase>43602d</separatorColorBase>
            <selectorColorBase>002105</selectorColorBase>
            <selectorColorEndBase>002105</selectorColorEndBase>
            <selectedColorBase>DDDDDD</selectedColorBase>
            <menuGroupTextColorBase>0f0031</menuGroupTextColorBase>
        </variables>
</theme>
